trendspyg/__init__.py
trendspyg/cli.py
trendspyg/config.py
trendspyg/downloader.py
trendspyg/exceptions.py
trendspyg/py.typed
trendspyg/rss_downloader.py
trendspyg/utils.py
trendspyg/version.py
trendspyg-0.4.2.dist-info/licenses/LICENSE
trendspyg-0.4.2.dist-info/METADATA
trendspyg-0.4.2.dist-info/WHEEL
trendspyg-0.4.2.dist-info/entry_points.txt
trendspyg-0.4.2.dist-info/top_level.txt
trendspyg-0.4.2.dist-info/RECORD
