Metadata-Version: 2.4
Name: trendspyg
Version: 0.4.2
Summary: Free, open-source Python library for real-time Google Trends data with CLI and API - pytrends alternative with 188K+ configurations
Author-email: flack0x <ali.marodis2@gmail.com>
License: MIT
Project-URL: Homepage, https://github.com/flack0x/trendspyg
Project-URL: Documentation, https://github.com/flack0x/trendspyg#readme
Project-URL: Repository, https://github.com/flack0x/trendspyg
Project-URL: Issues, https://github.com/flack0x/trendspyg/issues
Project-URL: Changelog, https://github.com/flack0x/trendspyg/blob/main/CHANGELOG.md
Keywords: google-trends,trends,pytrends,data-analysis,seo,marketing,analytics
Classifier: Development Status :: 3 - Alpha
Classifier: Intended Audience :: Developers
Classifier: Intended Audience :: Science/Research
Classifier: License :: OSI Approved :: MIT License
Classifier: Programming Language :: Python :: 3
Classifier: Programming Language :: Python :: 3.8
Classifier: Programming Language :: Python :: 3.9
Classifier: Programming Language :: Python :: 3.10
Classifier: Programming Language :: Python :: 3.11
Classifier: Programming Language :: Python :: 3.12
Classifier: Topic :: Internet
Classifier: Topic :: Software Development :: Libraries :: Python Modules
Classifier: Topic :: Scientific/Engineering :: Information Analysis
Requires-Python: >=3.8
License-File: LICENSE
Requires-Dist: selenium>=4.15.0
Requires-Dist: requests>=2.31.0
Provides-Extra: dev
Requires-Dist: pytest>=7.4.0; extra == "dev"
Requires-Dist: pytest-cov>=4.1.0; extra == "dev"
Requires-Dist: pytest-mock>=3.11.1; extra == "dev"
Requires-Dist: pytest-asyncio>=0.23.0; extra == "dev"
Requires-Dist: black>=23.7.0; extra == "dev"
Requires-Dist: flake8>=6.1.0; extra == "dev"
Requires-Dist: mypy>=1.5.0; extra == "dev"
Requires-Dist: isort>=5.12.0; extra == "dev"
Provides-Extra: cli
Requires-Dist: click>=8.0.0; extra == "cli"
Requires-Dist: tqdm>=4.65.0; extra == "cli"
Provides-Extra: async
Requires-Dist: aiohttp>=3.9.0; extra == "async"
Provides-Extra: analysis
Requires-Dist: pandas>=2.0.0; extra == "analysis"
Requires-Dist: pyarrow>=10.0.0; extra == "analysis"
Dynamic: license-file
